COPYING
MANIFEST.in
README
health_services_lab_view.xml
setup.py
./__init__.py
./health_services_lab.py
./health_services_lab_view.xml
./tryton.cfg
./doc/index.rst
./locale/ar.po
./locale/de.po
./locale/el.po
./locale/es.po
./locale/fr.po
./locale/it_IT.po
./locale/ja_JP.po
./locale/lo.po
./locale/pt_BR.po
./locale/zh_CN.po
./tests/__init__.py
./tests/test_health_services_lab.py
./view/gnuhealth_lab_request.xml
./view/gnuhealth_lab_start_request.xml
./wizard/__init__.py
./wizard/wizard_health_services.py
locale/ar.po
locale/de.po
locale/el.po
locale/es.po
locale/fr.po
locale/it_IT.po
locale/ja_JP.po
locale/lo.po
locale/pt_BR.po
locale/zh_CN.po
security/access_rights.xml
trytond_health_services_lab.egg-info/PKG-INFO
trytond_health_services_lab.egg-info/SOURCES.txt
trytond_health_services_lab.egg-info/dependency_links.txt
trytond_health_services_lab.egg-info/entry_points.txt
trytond_health_services_lab.egg-info/not-zip-safe
trytond_health_services_lab.egg-info/requires.txt
trytond_health_services_lab.egg-info/top_level.txt
view/gnuhealth_lab_request.xml
view/gnuhealth_lab_start_request.xml
wizard/create_health_service_invoice.xml